blackhole/__init__.py
blackhole/base.py
black_hole_gui-0.0.0.dev1.dist-info/LICENSE
black_hole_gui-0.0.0.dev1.dist-info/METADATA
black_hole_gui-0.0.0.dev1.dist-info/WHEEL
black_hole_gui-0.0.0.dev1.dist-info/top_level.txt
black_hole_gui-0.0.0.dev1.dist-info/RECORD
