Metadata-Version: 2.2
Name: black-hole-gui
Version: 0.0.0.dev1
Summary: A framework for creating data analysis GUIs that absorb all data within their event horizon.
Author-email: Grant Giesbrecht <grant.giesbrecht@colorado.edu>
Project-URL: Homepage, https://github.com/Grant-Giesbrecht/blackhole
Project-URL: Issues, https://github.com/Grant-Giesbrecht/blackhole/issues
Classifier: Programming Language :: Python :: 3
Classifier: License :: OSI Approved :: MIT License
Classifier: Operating System :: OS Independent
Requires-Python: >=3.10
License-File: LICENSE
Requires-Dist: matplotlib>=3.9.0
